{"BC-UG": {"rapportExprime": 28.53, "rapportInscrit": 14.71, "nombre": 4431, "nom": "Mme LE PEIH Nicole et M. MARCHAND Christophe"}, "inscrits": 30110, "votants": {"rapportInscrit": 54.77, "nombre": 16491}, "BC-UD": {"rapportExprime": 37.64, "rapportInscrit": 19.41, "nombre": 5846, "nom": "Mme PERRAULT Soizic et M. QUERO Beno\u00eet"}, "exprimes": {"rapportVotant": 94.18, "rapportInscrit": 51.58, "nombre": 15532}, "BC-DIV": {"rapportExprime": 3.7, "rapportInscrit": 1.9, "nombre": 575, "nom": "M. PASSAL Christian et Mme RAMEL Fran\u00e7oise"}, "BC-FG": {"rapportExprime": 8.43, "rapportInscrit": 4.35, "nombre": 1310, "nom": "Mme DORE-LUCAS Marie-Madeleine et M. LOCUSSOL Andr\u00e9"}, "blancs": {"rapportVotant": 3.85, "rapportInscrit": 2.11, "nombre": 635}, "nuls": {"rapportVotant": 1.96, "rapportInscrit": 1.08, "nombre": 324}, "abstentions": {"rapportInscrit": 45.23, "nombre": 13619}, "BC-FN": {"rapportExprime": 21.7, "rapportInscrit": 11.19, "nombre": 3370, "nom": "Mme ADOUE Evelyne et M. DESBOIS Thierry"}}