{"BC-UG": {"rapportExprime": 22.16, "rapportInscrit": 12.29, "nombre": 1984, "nom": "M. PLUCHOT Pierre et Mme ROCH Evelyne"}, "inscrits": 16136, "votants": {"rapportInscrit": 57.31, "nombre": 9247}, "BC-VEC": {"rapportExprime": 6.82, "rapportInscrit": 3.78, "nombre": 611, "nom": "Mme ROUX Diane et M. VIERNE Fabrice"}, "exprimes": {"rapportVotant": 96.82, "rapportInscrit": 55.48, "nombre": 8953}, "BC-UDI": {"rapportExprime": 50.17, "rapportInscrit": 27.83, "nombre": 4492, "nom": "M. DUBAY Jacques et Mme GAUCHER Sylvie"}, "blancs": {"rapportVotant": 2.1, "rapportInscrit": 1.2, "nombre": 194}, "nuls": {"rapportVotant": 1.08, "rapportInscrit": 0.62, "nombre": 100}, "abstentions": {"rapportInscrit": 42.69, "nombre": 6889}, "BC-FN": {"rapportExprime": 20.84, "rapportInscrit": 11.56, "nombre": 1866, "nom": "M. BRAUD Jean-Paul et Mme DE TESTA S\u00e9gol\u00e8ne"}}