{"blancs": {"rapportVotant": 3.42, "nombre": 373, "rapportInscrit": 1.78}, "votants": {"nombre": 10913, "rapportInscrit": 51.96}, "BC-UD": {"nombre": 3270, "nom": "Mme DE GIBON Sophie et M. MARTIN Patrice", "rapportExprime": 31.29, "rapportInscrit": 15.56}, "BC-FN": {"nombre": 2720, "nom": "Mme LEBOEUF Marie-Fran\u00e7oise et M. MAL Christophe", "rapportExprime": 26.03, "rapportInscrit": 12.95}, "exprimes": {"rapportVotant": 95.77, "nombre": 10451, "rapportInscrit": 49.76}, "nuls": {"rapportVotant": 0.82, "nombre": 89, "rapportInscrit": 0.42}, "abstentions": {"nombre": 10090, "rapportInscrit": 48.04}, "inscrits": 21003, "BC-UG": {"nombre": 4461, "nom": "Mme ARRUEGO Coralie et M. PI\u00c9LOT Christian", "rapportExprime": 42.68, "rapportInscrit": 21.23}}