{"BC-UG": {"rapportExprime": 34.2, "rapportInscrit": 15.49, "nombre": 5905, "nom": "Mme CATRAIN Isabelle et M. POUZOL Michel"}, "inscrits": 38114, "votants": {"rapportInscrit": 47.17, "nombre": 17980}, "BC-UD": {"rapportExprime": 34.33, "rapportInscrit": 15.55, "nombre": 5927, "nom": "M. M\u00c9ARY Nicolas et Mme RIGAULT Sophie"}, "exprimes": {"rapportVotant": 96.02, "rapportInscrit": 45.3, "nombre": 17265}, "BC-MDM": {"rapportExprime": 6.11, "rapportInscrit": 2.76, "nombre": 1055, "nom": "Mme GAUBIER Justine et M. MICOU Fabien"}, "blancs": {"rapportVotant": 2.76, "rapportInscrit": 1.3, "nombre": 496}, "nuls": {"rapportVotant": 1.22, "rapportInscrit": 0.57, "nombre": 219}, "abstentions": {"rapportInscrit": 52.83, "nombre": 20134}, "BC-FN": {"rapportExprime": 25.36, "rapportInscrit": 11.48, "nombre": 4378, "nom": "Mme DEGRELLE-KERLOCH Lydie et M. DUSSAUSAYE Ga\u00ebtan"}}