{"blancs": {"rapportVotant": 6.26, "nombre": 1166, "rapportInscrit": 2.84}, "votants": {"nombre": 18627, "rapportInscrit": 45.39}, "BC-FN": {"nombre": 5491, "nom": "M. HURTH Georges et Mme LONGUET Irina", "rapportExprime": 32.13, "rapportInscrit": 13.37}, "BC-UMP": {"nombre": 11600, "nom": "M. DE BELENET Arnaud et Mme POTTIEZ-HUSSON Val\u00e9rie", "rapportExprime": 67.87, "rapportInscrit": 28.26}, "exprimes": {"rapportVotant": 91.75, "nombre": 17091, "rapportInscrit": 41.64}, "nuls": {"rapportVotant": 1.99, "nombre": 370, "rapportInscrit": 0.9}, "abstentions": {"nombre": 22414, "rapportInscrit": 54.61}, "inscrits": 41041}