{"blancs": {"rapportVotant": 5.7, "nombre": 816, "rapportInscrit": 3.03}, "votants": {"nombre": 14310, "rapportInscrit": 53.12}, "BC-UD": {"nombre": 7269, "nom": "Mme MELZASSARD Corinne et M. NERAUD Fr\u00e9d\u00e9ric", "rapportExprime": 55.13, "rapportInscrit": 26.98}, "BC-FN": {"nombre": 5916, "nom": "M. CUIGNACHE Alexandre et Mme LEFORT Fanny", "rapportExprime": 44.87, "rapportInscrit": 21.96}, "exprimes": {"rapportVotant": 92.14, "nombre": 13185, "rapportInscrit": 48.94}, "nuls": {"rapportVotant": 2.16, "nombre": 309, "rapportInscrit": 1.15}, "abstentions": {"nombre": 12629, "rapportInscrit": 46.88}, "inscrits": 26939}