{"inscrits": 28593, "BC-FG": {"rapportExprime": 6.2, "rapportInscrit": 3.06, "nombre": 876, "nom": "Mme CAILLIEZ Monique et M. TOWMSEND Michel"}, "blancs": {"rapportVotant": 2.75, "rapportInscrit": 1.42, "nombre": 406}, "abstentions": {"rapportInscrit": 48.39, "nombre": 13836}, "BC-FN": {"rapportExprime": 33.08, "rapportInscrit": 16.35, "nombre": 4677, "nom": "Mme GORRE Isabelle et M. VERCUCQUE Rudy"}, "exprimes": {"rapportVotant": 95.82, "rapportInscrit": 49.45, "nombre": 14140}, "votants": {"rapportInscrit": 51.61, "nombre": 14757}, "BC-VEC": {"rapportExprime": 3.94, "rapportInscrit": 1.94, "nombre": 557, "nom": "Mme DEKEISTER Anne et M. P\u00c9LABON Marc"}, "BC-UD": {"rapportExprime": 20.78, "rapportInscrit": 10.27, "nombre": 2938, "nom": "Mme DUCLOY Mich\u00e8le et M. HOUDAYER Eric"}, "BC-SOC": {"rapportExprime": 32.72, "rapportInscrit": 16.17, "nombre": 4626, "nom": "M. LOQUET Ludovic et Mme MATRAT Caroline"}, "BC-EXD": {"rapportExprime": 3.3, "rapportInscrit": 1.62, "nombre": 466, "nom": "Mme DELEVALLET Monique et M. RECHE K\u00e9vin"}, "nuls": {"rapportVotant": 1.43, "rapportInscrit": 0.74, "nombre": 211}}