{"inscrits": 31451, "BC-FG": {"rapportExprime": 25.37, "rapportInscrit": 13.26, "nombre": 4173, "nom": "Mme CALUEBA-RIZZOLO V\u00e9ronique et M. LIBERTI Fran\u00e7ois"}, "blancs": {"rapportVotant": 1.43, "rapportInscrit": 0.77, "nombre": 242}, "abstentions": {"rapportInscrit": 46.26, "nombre": 14549}, "BC-FN": {"rapportExprime": 31.57, "rapportInscrit": 16.51, "nombre": 5194, "nom": "M. LIGUORI Ga\u00ebtan et Mme ROQUES Myriam"}, "exprimes": {"rapportVotant": 97.33, "rapportInscrit": 52.3, "nombre": 16450}, "votants": {"rapportInscrit": 53.74, "nombre": 16902}, "BC-VEC": {"rapportExprime": 5.46, "rapportInscrit": 2.85, "nombre": 898, "nom": "Mme ALAMARTINE Fran\u00e7oise et M. HERC\u00c9 Laurent"}, "BC-UD": {"rapportExprime": 23.65, "rapportInscrit": 12.37, "nombre": 3891, "nom": "M. FERRARA Romain et Mme ROUCOULET Pierrette"}, "BC-DLF": {"rapportExprime": 4.91, "rapportInscrit": 2.56, "nombre": 808, "nom": "M. FERRARA Enzo et Mme GUIGOU Marie-Fran\u00e7oise"}, "BC-SOC": {"rapportExprime": 9.03, "rapportInscrit": 4.72, "nombre": 1486, "nom": "M. DOUCET Jean-Louis et Mme MAUROY V\u00e9ronique"}, "nuls": {"rapportVotant": 1.24, "rapportInscrit": 0.67, "nombre": 210}}