{"blancs": {"rapportVotant": 6.25, "nombre": 450, "rapportInscrit": 3.69}, "votants": {"nombre": 7205, "rapportInscrit": 59.04}, "BC-UMP": {"nombre": 3621, "nom": "M. DELPECH Jean-Jacques et Mme TAURISSON Nicole", "rapportExprime": 55.89, "rapportInscrit": 29.67}, "exprimes": {"rapportVotant": 89.92, "nombre": 6479, "rapportInscrit": 53.09}, "nuls": {"rapportVotant": 3.83, "nombre": 276, "rapportInscrit": 2.26}, "abstentions": {"nombre": 4998, "rapportInscrit": 40.96}, "inscrits": 12203, "BC-SOC": {"nombre": 2858, "nom": "Mme DAVID Isabelle et M. ROQUES Guy", "rapportExprime": 44.11, "rapportInscrit": 23.42}}