{"inscrits": 8980, "votants": {"rapportInscrit": 59.78, "nombre": 5368}, "BC-SOC": {"rapportExprime": 32.86, "rapportInscrit": 18.64, "nombre": 1674, "nom": "M. BAZIN Fabien et Mme VERIN Anne"}, "exprimes": {"rapportVotant": 94.91, "rapportInscrit": 56.74, "nombre": 5095}, "BC-FG": {"rapportExprime": 8.73, "rapportInscrit": 4.95, "nombre": 445, "nom": "Mme LIRON Isabelle et M. RIVIERE Herv\u00e9"}, "blancs": {"rapportVotant": 2.78, "rapportInscrit": 1.66, "nombre": 149}, "nuls": {"rapportVotant": 2.31, "rapportInscrit": 1.38, "nombre": 124}, "abstentions": {"rapportInscrit": 40.22, "nombre": 3612}, "BC-FN": {"rapportExprime": 25.34, "rapportInscrit": 14.37, "nombre": 1291, "nom": "Mme APRICENA C\u00e9line et M. STEPHAN Marcel"}, "BC-DVD": {"rapportExprime": 33.07, "rapportInscrit": 18.76, "nombre": 1685, "nom": "Mme BREZA-SOUDAN Maria et M. ROCHARD Jean-Charles"}}