{"BC-UG": {"rapportExprime": 52.17, "rapportInscrit": 23.6, "nombre": 3946, "nom": "M. BOUTANT Michel et Mme LAVIE-CAMBOT Maryse"}, "inscrits": 16718, "votants": {"rapportInscrit": 51.04, "nombre": 8533}, "BC-UD": {"rapportExprime": 32.1, "rapportInscrit": 14.52, "nombre": 2428, "nom": "Mme COMBEAU Danielle et M. DE LORGERIL Dominique"}, "exprimes": {"rapportVotant": 88.64, "rapportInscrit": 45.24, "nombre": 7564}, "BC-FG": {"rapportExprime": 15.73, "rapportInscrit": 7.11, "nombre": 1190, "nom": "Mme BOURDIER Nicolle et M. MERLE R\u00e9my"}, "blancs": {"rapportVotant": 6.32, "rapportInscrit": 3.22, "nombre": 539}, "nuls": {"rapportVotant": 5.04, "rapportInscrit": 2.57, "nombre": 430}, "abstentions": {"rapportInscrit": 48.96, "nombre": 8185}}