{"blancs": {"rapportVotant": 6.43, "nombre": 741, "rapportInscrit": 3.31}, "votants": {"nombre": 11528, "rapportInscrit": 51.5}, "BC-UD": {"nombre": 6045, "nom": "M. DUMONTIER Arnaud et Mme FOYART Khristine", "rapportExprime": 57.36, "rapportInscrit": 27.0}, "BC-FN": {"nombre": 4493, "nom": "Mme BONNET Val\u00e9rie et M. ROSSIGNOL Reynald", "rapportExprime": 42.64, "rapportInscrit": 20.07}, "exprimes": {"rapportVotant": 91.41, "nombre": 10538, "rapportInscrit": 47.08}, "nuls": {"rapportVotant": 2.16, "nombre": 249, "rapportInscrit": 1.11}, "abstentions": {"nombre": 10857, "rapportInscrit": 48.5}, "inscrits": 22385}