{"blancs": {"rapportVotant": 4.02, "nombre": 446, "rapportInscrit": 2.14}, "votants": {"nombre": 11081, "rapportInscrit": 53.11}, "BC-FN": {"nombre": 4811, "nom": "M. DE LA TOCNAYE Thibaut et Mme MESL\u00c9 Leslie", "rapportExprime": 46.08, "rapportInscrit": 23.05}, "BC-UMP": {"nombre": 5630, "nom": "Mme AMOROS Elisabeth et M. BLANC Jean-Baptiste", "rapportExprime": 53.92, "rapportInscrit": 26.98}, "exprimes": {"rapportVotant": 94.22, "nombre": 10441, "rapportInscrit": 50.04}, "nuls": {"rapportVotant": 1.75, "nombre": 194, "rapportInscrit": 0.93}, "abstentions": {"nombre": 9783, "rapportInscrit": 46.89}, "inscrits": 20864}