{"blancs": {"rapportVotant": 4.39, "nombre": 516, "rapportInscrit": 2.04}, "votants": {"nombre": 11747, "rapportInscrit": 46.54}, "BC-UD": {"nombre": 6141, "nom": "Mme MARCHAL-TARNUS Corinne et M. PENSALFINI Eric", "rapportExprime": 55.84, "rapportInscrit": 24.32}, "exprimes": {"rapportVotant": 93.62, "nombre": 10998, "rapportInscrit": 43.57}, "nuls": {"rapportVotant": 1.98, "nombre": 233, "rapportInscrit": 0.92}, "abstentions": {"nombre": 13496, "rapportInscrit": 53.46}, "inscrits": 25243, "BC-SOC": {"nombre": 4857, "nom": "Mme GRUET St\u00e9phanie et M. RUHLAND Gr\u00e9goire", "rapportExprime": 44.16, "rapportInscrit": 19.24}}