{"inscrits": 17469, "votants": {"rapportInscrit": 40.96, "nombre": 7156}, "BC-SOC": {"rapportExprime": 14.18, "rapportInscrit": 5.54, "nombre": 968, "nom": "Mme DA CUNHA Christine et M. PETITCLAIR Guillaume"}, "BC-UD": {"rapportExprime": 20.68, "rapportInscrit": 8.08, "nombre": 1412, "nom": "Mme GUILLOTIN V\u00e9ronique et M. HOTTIER Jean-Louis"}, "exprimes": {"rapportVotant": 95.42, "rapportInscrit": 39.09, "nombre": 6828}, "BC-FG": {"rapportExprime": 40.0, "rapportInscrit": 15.63, "nombre": 2731, "nom": "M. CASONI Alain et Mme SILVESTRI Annie"}, "blancs": {"rapportVotant": 3.19, "rapportInscrit": 1.31, "nombre": 228}, "nuls": {"rapportVotant": 1.4, "rapportInscrit": 0.57, "nombre": 100}, "abstentions": {"rapportInscrit": 59.04, "nombre": 10313}, "BC-FN": {"rapportExprime": 25.15, "rapportInscrit": 9.82, "nombre": 1717, "nom": "Mme DECAILLOZ Martine et M. PINTO Patrick"}}