{"blancs": {"rapportVotant": 7.2, "nombre": 568, "rapportInscrit": 2.85}, "votants": {"nombre": 7886, "rapportInscrit": 39.58}, "BC-UMP": {"nombre": 3909, "nom": "Mme ABONDANCE Jocelyne et M. ROLLAND Vincent", "rapportExprime": 55.53, "rapportInscrit": 19.61}, "exprimes": {"rapportVotant": 89.27, "nombre": 7040, "rapportInscrit": 35.33}, "nuls": {"rapportVotant": 3.53, "nombre": 278, "rapportInscrit": 1.4}, "abstentions": {"nombre": 12040, "rapportInscrit": 60.42}, "inscrits": 19926, "BC-DVD": {"nombre": 3131, "nom": "M. NIVELLE Philippe et Mme PAVIET Marie-Christine", "rapportExprime": 44.47, "rapportInscrit": 15.71}}