{"BC-FG": {"rapportExprime": 6.75, "rapportInscrit": 3.15, "nombre": 384, "nom": "M. LEROY Robert et Mme RICHARD Monique"}, "inscrits": 12188, "votants": {"rapportInscrit": 48.15, "nombre": 5868}, "BC-VEC": {"rapportExprime": 14.09, "rapportInscrit": 6.57, "nombre": 801, "nom": "Mme JAUMAIN Fran\u00e7oise et M. SELLAM Guy"}, "exprimes": {"rapportVotant": 96.9, "rapportInscrit": 46.65, "nombre": 5686}, "BC-SOC": {"rapportExprime": 22.72, "rapportInscrit": 10.6, "nombre": 1292, "nom": "M. CERINO Jean-Beno\u00eet et Mme SOBKOWIAK Christine"}, "BC-UMP": {"rapportExprime": 39.36, "rapportInscrit": 18.36, "nombre": 2238, "nom": "Mme BOCHATON Brigitte et M. BOUVARD Michel"}, "blancs": {"rapportVotant": 1.89, "rapportInscrit": 0.91, "nombre": 111}, "nuls": {"rapportVotant": 1.21, "rapportInscrit": 0.58, "nombre": 71}, "abstentions": {"rapportInscrit": 51.85, "nombre": 6320}, "BC-FN": {"rapportExprime": 17.08, "rapportInscrit": 7.96, "nombre": 971, "nom": "Mme COLAS H\u00e9l\u00e8ne et M. MORET Pascal"}}