{"blancs": {"rapportVotant": 5.86, "nombre": 1090, "rapportInscrit": 2.49}, "votants": {"nombre": 18597, "rapportInscrit": 42.54}, "BC-UG": {"nombre": 5497, "nom": "Mme COTORA Maria et M. ELIE Jean-Philippe", "rapportExprime": 31.53, "rapportInscrit": 12.57}, "exprimes": {"rapportVotant": 93.75, "nombre": 17435, "rapportInscrit": 39.88}, "nuls": {"rapportVotant": 0.39, "nombre": 72, "rapportInscrit": 0.16}, "abstentions": {"nombre": 25121, "rapportInscrit": 57.46}, "inscrits": 43718, "BC-UD": {"nombre": 11938, "nom": "M. COURT\u00c8S Daniel et Mme LIMOGE Marie-Pierre", "rapportExprime": 68.47, "rapportInscrit": 27.3}}