{"blancs": {"rapportVotant": 7.32, "nombre": 386, "rapportInscrit": 3.9}, "votants": {"nombre": 5270, "rapportInscrit": 53.28}, "BC-UD": {"nombre": 3293, "nom": "M. BLOUET Jean-Pierre et Mme DE VALLAMBRAS Marie-Th\u00e9r\u00e8se", "rapportExprime": 70.36, "rapportInscrit": 33.28}, "BC-FN": {"nombre": 1387, "nom": "Mme CHEVREAU Josette et M. ROBERT Jean-Pierre", "rapportExprime": 29.64, "rapportInscrit": 14.02}, "exprimes": {"rapportVotant": 88.8, "nombre": 4680, "rapportInscrit": 47.31}, "nuls": {"rapportVotant": 3.87, "nombre": 204, "rapportInscrit": 2.06}, "abstentions": {"nombre": 4622, "rapportInscrit": 46.72}, "inscrits": 9892}