{"blancs": {"rapportVotant": 7.61, "nombre": 621, "rapportInscrit": 4.01}, "votants": {"nombre": 8162, "rapportInscrit": 52.72}, "BC-UD": {"nombre": 4401, "nom": "M. DANCOURT Vincent et Mme MEHEU Christelle", "rapportExprime": 60.11, "rapportInscrit": 28.42}, "BC-FN": {"nombre": 2921, "nom": "Mme BAUDOIN Fran\u00e7oise et M. TALLEC \u00c9ric", "rapportExprime": 39.89, "rapportInscrit": 18.86}, "exprimes": {"rapportVotant": 89.71, "nombre": 7322, "rapportInscrit": 47.29}, "nuls": {"rapportVotant": 2.68, "nombre": 219, "rapportInscrit": 1.41}, "abstentions": {"nombre": 7321, "rapportInscrit": 47.28}, "inscrits": 15483}