{"blancs": {"rapportVotant": 8.5, "nombre": 945, "rapportInscrit": 4.66}, "votants": {"nombre": 11113, "rapportInscrit": 54.75}, "BC-UD": {"nombre": 6378, "nom": "Mme RICHARD Christine et M. THOMAS Laurent", "rapportExprime": 64.8, "rapportInscrit": 31.42}, "BC-FN": {"nombre": 3464, "nom": "Mme BEAULIEU Sylvie et M. GAILLARD Franck", "rapportExprime": 35.2, "rapportInscrit": 17.06}, "exprimes": {"rapportVotant": 88.56, "nombre": 9842, "rapportInscrit": 48.49}, "nuls": {"rapportVotant": 2.93, "nombre": 326, "rapportInscrit": 1.61}, "abstentions": {"nombre": 9184, "rapportInscrit": 45.25}, "inscrits": 20297}