{"blancs": {"rapportVotant": 5.14, "nombre": 650, "rapportInscrit": 2.56}, "votants": {"nombre": 12638, "rapportInscrit": 49.76}, "BC-UD": {"nombre": 6785, "nom": "Mme ESTROSI-SASSONE Dominique et M. SCIBETTA Charles", "rapportExprime": 57.83, "rapportInscrit": 26.71}, "BC-FN": {"nombre": 4947, "nom": "Mme BRONDOLIN Audrey et M. THOORIS Michel", "rapportExprime": 42.17, "rapportInscrit": 19.47}, "exprimes": {"rapportVotant": 92.83, "nombre": 11732, "rapportInscrit": 46.2}, "nuls": {"rapportVotant": 2.03, "nombre": 256, "rapportInscrit": 1.01}, "abstentions": {"nombre": 12758, "rapportInscrit": 50.24}, "inscrits": 25396}