{"inscrits": 14732, "votants": {"rapportInscrit": 42.59, "nombre": 6275}, "BC-DVG": {"rapportExprime": 12.39, "rapportInscrit": 4.86, "nombre": 716, "nom": "Mme DINANE Cynthia et M. PANCREL Bernard"}, "BC-FN": {"rapportExprime": 5.47, "rapportInscrit": 2.14, "nombre": 316, "nom": "Mme QUENTIN Sylvie et M. VIENNET Stephan"}, "exprimes": {"rapportVotant": 92.08, "rapportInscrit": 39.22, "nombre": 5778}, "BC-UMP": {"rapportExprime": 50.22, "rapportInscrit": 19.69, "nombre": 2902, "nom": "M. BERNIER Laurent et Mme ROBERT LAMPONI Baptistia"}, "blancs": {"rapportVotant": 3.76, "rapportInscrit": 1.6, "nombre": 236}, "nuls": {"rapportVotant": 4.16, "rapportInscrit": 1.77, "nombre": 261}, "abstentions": {"rapportInscrit": 57.41, "nombre": 8457}, "BC-PG": {"rapportExprime": 18.26, "rapportInscrit": 7.16, "nombre": 1055, "nom": "Mme PEROUMAL SYLVANISE Sophie et M. SUEDOIS Jean"}}