{"blancs": {"rapportVotant": 6.24, "nombre": 837, "rapportInscrit": 2.94}, "votants": {"nombre": 13419, "rapportInscrit": 47.13}, "BC-DVG": {"nombre": 9062, "nom": "Mme DRAY-FITOUSSI Mich\u00e8le et M. TORTORICI Sauveur", "rapportExprime": 73.81, "rapportInscrit": 31.82}, "BC-FN": {"nombre": 3215, "nom": "M. BENGLIA Jean-Paul et Mme GOELLER Jocelyne", "rapportExprime": 26.19, "rapportInscrit": 11.29}, "exprimes": {"rapportVotant": 91.49, "nombre": 12277, "rapportInscrit": 43.12}, "nuls": {"rapportVotant": 2.27, "nombre": 305, "rapportInscrit": 1.07}, "abstentions": {"nombre": 15056, "rapportInscrit": 52.87}, "inscrits": 28475}