{"blancs": {"rapportVotant": 7.92, "nombre": 867, "rapportInscrit": 4.33}, "votants": {"nombre": 10941, "rapportInscrit": 54.68}, "BC-UD": {"nombre": 5851, "nom": "M. GRAS Fr\u00e9d\u00e9ric et Mme PEYRIC Marie-Christine", "rapportExprime": 60.69, "rapportInscrit": 29.24}, "BC-FN": {"nombre": 3790, "nom": "Mme BERNARD R\u00e9gine et M. BOULET J\u00e9r\u00e9mie", "rapportExprime": 39.31, "rapportInscrit": 18.94}, "exprimes": {"rapportVotant": 88.12, "nombre": 9641, "rapportInscrit": 48.18}, "nuls": {"rapportVotant": 3.96, "nombre": 433, "rapportInscrit": 2.16}, "abstentions": {"nombre": 9068, "rapportInscrit": 45.32}, "inscrits": 20009}