{"blancs": {"rapportVotant": 5.35, "nombre": 168, "rapportInscrit": 2.65}, "votants": {"nombre": 3138, "rapportInscrit": 49.42}, "exprimes": {"rapportVotant": 90.47, "nombre": 2839, "rapportInscrit": 44.71}, "nuls": {"rapportVotant": 4.17, "nombre": 131, "rapportInscrit": 2.06}, "abstentions": {"nombre": 3212, "rapportInscrit": 50.58}, "inscrits": 6350, "BC-SOC": {"nombre": 806, "nom": "Mme ALBERTINI Laura et M. GERONIMI Jean", "rapportExprime": 28.39, "rapportInscrit": 12.69}, "BC-DVD": {"nombre": 2033, "nom": "Mme LE BOMIN Vanina et M. ROSSI Michel", "rapportExprime": 71.61, "rapportInscrit": 32.01}}