{"blancs": {"rapportVotant": 4.61, "nombre": 548, "rapportInscrit": 2.31}, "votants": {"nombre": 11888, "rapportInscrit": 50.13}, "BC-UD": {"nombre": 6862, "nom": "M. JALU Michel et Mme LE BRETON Marie-Jos\u00e9", "rapportExprime": 62.57, "rapportInscrit": 28.93}, "exprimes": {"rapportVotant": 92.25, "nombre": 10967, "rapportInscrit": 46.25}, "nuls": {"rapportVotant": 3.14, "nombre": 373, "rapportInscrit": 1.57}, "abstentions": {"nombre": 11824, "rapportInscrit": 49.87}, "inscrits": 23712, "BC-UG": {"nombre": 4105, "nom": "Mme GUILLAS Martine et M. ROUSSEL Guy", "rapportExprime": 37.43, "rapportInscrit": 17.31}}