{"blancs": {"rapportVotant": 8.22, "nombre": 1372, "rapportInscrit": 3.8}, "votants": {"nombre": 16692, "rapportInscrit": 46.22}, "BC-UD": {"nombre": 10114, "nom": "M. MEHLHORN Eric et Mme VERMILLET Brigitte", "rapportExprime": 68.21, "rapportInscrit": 28.0}, "BC-FN": {"nombre": 4714, "nom": "M. FESLER Michel et Mme GUIBERT Audrey", "rapportExprime": 31.79, "rapportInscrit": 13.05}, "exprimes": {"rapportVotant": 88.83, "nombre": 14828, "rapportInscrit": 41.06}, "nuls": {"rapportVotant": 2.95, "nombre": 492, "rapportInscrit": 1.36}, "abstentions": {"nombre": 19425, "rapportInscrit": 53.78}, "inscrits": 36117}