{"inscrits": 15924, "votants": {"rapportInscrit": 51.93, "nombre": 8270}, "BC-UD": {"rapportExprime": 18.27, "rapportInscrit": 9.03, "nombre": 1439, "nom": "Mme COSSON St\u00e9phanie et M. COTTERRE Yvon"}, "exprimes": {"rapportVotant": 95.22, "rapportInscrit": 49.45, "nombre": 7875}, "BC-MDM": {"rapportExprime": 10.4, "rapportInscrit": 5.14, "nombre": 819, "nom": "Mme DURAND-BOUJU Laura et M. POTENNEC G\u00e9rard"}, "blancs": {"rapportVotant": 3.3, "rapportInscrit": 1.71, "nombre": 273}, "nuls": {"rapportVotant": 1.48, "rapportInscrit": 0.77, "nombre": 122}, "abstentions": {"rapportInscrit": 48.07, "nombre": 7654}, "BC-FN": {"rapportExprime": 31.68, "rapportInscrit": 15.66, "nombre": 2495, "nom": "M. DE LACOSTE LAREYMONDIE Jean-Marc et Mme TEXIER Isabelle"}, "BC-RDG": {"rapportExprime": 39.64, "rapportInscrit": 19.6, "nombre": 3122, "nom": "M. FERCHAUD Pascal et Mme GUILLEN Ghislaine"}}