{"blancs": {"rapportVotant": 11.35, "nombre": 972, "rapportInscrit": 4.49}, "votants": {"nombre": 8565, "rapportInscrit": 39.57}, "BC-UD": {"nombre": 4499, "nom": "Mme FIRMIN LE BODO Agn\u00e8s et M. TEISSERE Patrick", "rapportExprime": 59.25, "rapportInscrit": 20.78}, "BC-RDG": {"nombre": 3094, "nom": "Mme FERNEZ Henriette et M. SIFFERT Antoine", "rapportExprime": 40.75, "rapportInscrit": 14.29}, "exprimes": {"rapportVotant": 88.65, "nombre": 7593, "rapportInscrit": 35.08}, "nuls": {"rapportVotant": 0.0, "nombre": 0, "rapportInscrit": 0.0}, "abstentions": {"nombre": 13081, "rapportInscrit": 60.43}, "inscrits": 21646}