{"BC-UG": {"rapportExprime": 31.61, "rapportInscrit": 17.35, "nombre": 5389, "nom": "M. BAGNERIS Bernard et Mme PRUVOT Muriel"}, "inscrits": 31045, "votants": {"rapportInscrit": 57.46, "nombre": 17839}, "BC-DVG": {"rapportExprime": 6.74, "rapportInscrit": 3.7, "nombre": 1150, "nom": "M. BARBY Thomas et Mme FLECHER Dominique"}, "BC-VEC": {"rapportExprime": 11.07, "rapportInscrit": 6.07, "nombre": 1887, "nom": "Mme DOERLER B\u00e9reng\u00e8re et M. SARRAILH Michel"}, "exprimes": {"rapportVotant": 95.58, "rapportInscrit": 54.92, "nombre": 17050}, "blancs": {"rapportVotant": 3.58, "rapportInscrit": 2.06, "nombre": 638}, "nuls": {"rapportVotant": 0.85, "rapportInscrit": 0.49, "nombre": 151}, "abstentions": {"rapportInscrit": 42.54, "nombre": 13206}, "BC-FN": {"rapportExprime": 16.49, "rapportInscrit": 9.05, "nombre": 2812, "nom": "M. GOUIN Eric et Mme LOPAU Marie"}, "BC-DVD": {"rapportExprime": 34.09, "rapportInscrit": 18.72, "nombre": 5812, "nom": "Mme BARRAL Elisabeth et M. LAFON Arnaud"}}