{"BC-UG": {"rapportExprime": 31.09, "rapportInscrit": 16.92, "nombre": 2855, "nom": "M. FOGNINI Jean-Marc et Mme GUILLON Pascale"}, "inscrits": 16868, "votants": {"rapportInscrit": 56.8, "nombre": 9581}, "BC-UD": {"rapportExprime": 33.99, "rapportInscrit": 18.5, "nombre": 3122, "nom": "M. HEDON Jean-Yves et Mme TARDY Car\u00e8ne"}, "exprimes": {"rapportVotant": 95.86, "rapportInscrit": 54.45, "nombre": 9184}, "BC-COM": {"rapportExprime": 7.98, "rapportInscrit": 4.34, "nombre": 733, "nom": "Mme ORSAZ Fran\u00e7oise et M. THOUMINE Yves"}, "blancs": {"rapportVotant": 3.1, "rapportInscrit": 1.76, "nombre": 297}, "nuls": {"rapportVotant": 1.04, "rapportInscrit": 0.59, "nombre": 100}, "abstentions": {"rapportInscrit": 43.2, "nombre": 7287}, "BC-FN": {"rapportExprime": 26.94, "rapportInscrit": 14.66, "nombre": 2474, "nom": "M. MARI\u00c9 Patrick et Mme MAYET Jocelyne"}}