{"lastUpdateDateTime": "23/03/2015 17:23", "results": {"BC-UG": {"rapportExprime": 13.92, "rapportInscrit": 7.78, "nombre": 11187}, "inscrits": 143860, "BC-UC": {"rapportExprime": 2.27, "rapportInscrit": 1.27, "nombre": 1826}, "BC-FG": {"rapportExprime": 7.1, "rapportInscrit": 3.97, "nombre": 5705}, "blancs": {"rapportVotant": 4.44, "rapportInscrit": 2.67, "nombre": 3839}, "BC-DIV": {"rapportExprime": 2.82, "rapportInscrit": 1.58, "nombre": 2270}, "abstentions": {"rapportInscrit": 39.89, "nombre": 57381}, "BC-FN": {"rapportExprime": 10.16, "rapportInscrit": 5.68, "nombre": 8165}, "BC-DVD": {"rapportExprime": 23.57, "rapportInscrit": 13.17, "nombre": 18943}, "exprimes": {"rapportVotant": 92.95, "rapportInscrit": 55.87, "nombre": 80381}, "votants": {"rapportInscrit": 60.11, "nombre": 86479}, "BC-DVG": {"rapportExprime": 2.84, "rapportInscrit": 1.59, "nombre": 2284}, "BC-VEC": {"rapportExprime": 2.08, "rapportInscrit": 1.16, "nombre": 1674}, "BC-UD": {"rapportExprime": 1.7, "rapportInscrit": 0.95, "nombre": 1364}, "BC-SOC": {"rapportExprime": 24.81, "rapportInscrit": 13.86, "nombre": 19944}, "BC-UMP": {"rapportExprime": 8.73, "rapportInscrit": 4.88, "nombre": 7019}, "nuls": {"rapportVotant": 2.61, "rapportInscrit": 1.57, "nombre": 2259}}}