{"lastUpdateDateTime": "23/03/2015 17:23", "results": {"BC-UG": {"rapportExprime": 4.27, "rapportInscrit": 2.07, "nombre": 8711}, "inscrits": 420269, "BC-FG": {"rapportExprime": 2.58, "rapportInscrit": 1.25, "nombre": 5266}, "blancs": {"rapportVotant": 3.15, "rapportInscrit": 1.6, "nombre": 6736}, "BC-DIV": {"rapportExprime": 0.25, "rapportInscrit": 0.12, "nombre": 518}, "abstentions": {"rapportInscrit": 49.12, "nombre": 206451}, "BC-FN": {"rapportExprime": 23.38, "rapportInscrit": 11.36, "nombre": 47723}, "BC-DVD": {"rapportExprime": 1.41, "rapportInscrit": 0.68, "nombre": 2869}, "exprimes": {"rapportVotant": 95.46, "rapportInscrit": 48.57, "nombre": 204118}, "votants": {"rapportInscrit": 50.88, "nombre": 213818}, "BC-DVG": {"rapportExprime": 9.99, "rapportInscrit": 4.85, "nombre": 20386}, "BC-VEC": {"rapportExprime": 0.41, "rapportInscrit": 0.2, "nombre": 844}, "BC-UD": {"rapportExprime": 35.57, "rapportInscrit": 17.28, "nombre": 72602}, "BC-COM": {"rapportExprime": 0.6, "rapportInscrit": 0.29, "nombre": 1215}, "BC-DLF": {"rapportExprime": 0.24, "rapportInscrit": 0.11, "nombre": 481}, "BC-SOC": {"rapportExprime": 21.15, "rapportInscrit": 10.27, "nombre": 43175}, "nuls": {"rapportVotant": 1.39, "rapportInscrit": 0.71, "nombre": 2964}, "BC-EXG": {"rapportExprime": 0.16, "rapportInscrit": 0.08, "nombre": 328}}}