{"lastUpdateDateTime": "23/03/2015 17:23", "results": {"inscrits": 313765, "blancs": {"rapportVotant": 2.58, "rapportInscrit": 1.26, "nombre": 3959}, "BC-FG": {"rapportExprime": 1.27, "rapportInscrit": 0.6, "nombre": 1875}, "BC-UDI": {"rapportExprime": 13.94, "rapportInscrit": 6.57, "nombre": 20627}, "BC-UC": {"rapportExprime": 1.24, "rapportInscrit": 0.58, "nombre": 1829}, "abstentions": {"rapportInscrit": 51.05, "nombre": 160180}, "BC-FN": {"rapportExprime": 28.61, "rapportInscrit": 13.5, "nombre": 42346}, "BC-DVD": {"rapportExprime": 3.32, "rapportInscrit": 1.57, "nombre": 4911}, "exprimes": {"rapportVotant": 96.37, "rapportInscrit": 47.17, "nombre": 148013}, "votants": {"rapportInscrit": 48.95, "nombre": 153585}, "BC-DVG": {"rapportExprime": 9.25, "rapportInscrit": 4.36, "nombre": 13692}, "BC-VEC": {"rapportExprime": 0.82, "rapportInscrit": 0.39, "nombre": 1219}, "BC-UD": {"rapportExprime": 6.99, "rapportInscrit": 3.3, "nombre": 10341}, "BC-DLF": {"rapportExprime": 0.64, "rapportInscrit": 0.3, "nombre": 952}, "BC-SOC": {"rapportExprime": 12.19, "rapportInscrit": 5.75, "nombre": 18046}, "BC-UMP": {"rapportExprime": 21.74, "rapportInscrit": 10.25, "nombre": 32175}, "nuls": {"rapportVotant": 1.05, "rapportInscrit": 0.51, "nombre": 1613}}}