{"blancs": {"rapportVotant": 7.5, "nombre": 469, "rapportInscrit": 4.04}, "votants": {"nombre": 6251, "rapportInscrit": 53.87}, "BC-FN": {"nombre": 1623, "nom": "M. DELASALLE Gilles et Mme PADIOLEAU Reine", "rapportExprime": 29.46, "rapportInscrit": 13.98}, "exprimes": {"rapportVotant": 88.13, "nombre": 5509, "rapportInscrit": 47.48}, "nuls": {"rapportVotant": 4.37, "nombre": 273, "rapportInscrit": 2.35}, "abstentions": {"nombre": 5352, "rapportInscrit": 46.13}, "inscrits": 11603, "BC-SOC": {"nombre": 3886, "nom": "M. GLAVANY Jean et Mme ISSON Genevi\u00e8ve", "rapportExprime": 70.54, "rapportInscrit": 33.49}}