{"lastUpdateDateTime": "29/03/2015 21:37", "results": {"blancs": {"rapportVotant": 6.47, "nombre": 4526, "rapportInscrit": 3.46}, "votants": {"nombre": 69966, "rapportInscrit": 53.46}, "BC-UG": {"nombre": 6646, "rapportExprime": 10.56, "rapportInscrit": 5.08}, "BC-FN": {"nombre": 14091, "rapportExprime": 22.38, "rapportInscrit": 10.77}, "exprimes": {"rapportVotant": 89.99, "nombre": 62964, "rapportInscrit": 48.11}, "nuls": {"rapportVotant": 3.54, "nombre": 2476, "rapportInscrit": 1.89}, "abstentions": {"nombre": 60921, "rapportInscrit": 46.54}, "inscrits": 130887, "BC-UD": {"nombre": 33844, "rapportExprime": 53.75, "rapportInscrit": 25.86}, "BC-SOC": {"nombre": 8383, "rapportExprime": 13.31, "rapportInscrit": 6.4}}}