{"lastUpdateDateTime": "29/03/2015 23:28", "results": {"blancs": {"rapportVotant": 5.7, "nombre": 26487, "rapportInscrit": 2.77}, "votants": {"nombre": 465056, "rapportInscrit": 48.59}, "BC-UG": {"nombre": 14467, "rapportExprime": 3.39, "rapportInscrit": 1.51}, "BC-DVG": {"nombre": 52288, "rapportExprime": 12.26, "rapportInscrit": 5.46}, "BC-FN": {"nombre": 10702, "rapportExprime": 2.51, "rapportInscrit": 1.12}, "exprimes": {"rapportVotant": 91.74, "nombre": 426659, "rapportInscrit": 44.58}, "nuls": {"rapportVotant": 2.56, "nombre": 11910, "rapportInscrit": 1.24}, "abstentions": {"nombre": 492070, "rapportInscrit": 51.41}, "inscrits": 957126, "BC-UD": {"nombre": 208605, "rapportExprime": 48.89, "rapportInscrit": 21.79}, "BC-SOC": {"nombre": 140597, "rapportExprime": 32.95, "rapportInscrit": 14.69}}}