{"lastUpdateDateTime": "29/03/2015 21:44", "results": {"blancs": {"rapportVotant": 4.34, "nombre": 8655, "rapportInscrit": 2.54}, "exprimes": {"rapportVotant": 93.15, "nombre": 185851, "rapportInscrit": 54.64}, "BC-UD": {"nombre": 23856, "rapportExprime": 12.84, "rapportInscrit": 7.01}, "inscrits": 340163, "votants": {"nombre": 199518, "rapportInscrit": 58.65}, "BC-DIV": {"nombre": 5771, "rapportExprime": 3.11, "rapportInscrit": 1.7}, "BC-COM": {"nombre": 4665, "rapportExprime": 2.51, "rapportInscrit": 1.37}, "nuls": {"rapportVotant": 2.51, "nombre": 5012, "rapportInscrit": 1.47}, "BC-UG": {"nombre": 14980, "rapportExprime": 8.06, "rapportInscrit": 4.4}, "BC-FN": {"nombre": 64147, "rapportExprime": 34.52, "rapportInscrit": 18.86}, "BC-UMP": {"nombre": 25831, "rapportExprime": 13.9, "rapportInscrit": 7.59}, "abstentions": {"nombre": 140645, "rapportInscrit": 41.35}, "BC-DVD": {"nombre": 11530, "rapportExprime": 6.2, "rapportInscrit": 3.39}, "BC-SOC": {"nombre": 35071, "rapportExprime": 18.87, "rapportInscrit": 10.31}}}