{"blancs": {"rapportVotant": 7.19, "nombre": 1216, "rapportInscrit": 3.09}, "votants": {"nombre": 16916, "rapportInscrit": 42.96}, "BC-FN": {"nombre": 5667, "nom": "Mme CAPDET Maryline et M. OUCHIKH Karim", "rapportExprime": 37.25, "rapportInscrit": 14.39}, "BC-UMP": {"nombre": 9548, "nom": "M. DESSE Daniel et Mme RAFAITIN Agn\u00e8s", "rapportExprime": 62.75, "rapportInscrit": 24.24}, "exprimes": {"rapportVotant": 89.94, "nombre": 15215, "rapportInscrit": 38.64}, "nuls": {"rapportVotant": 2.87, "nombre": 485, "rapportInscrit": 1.23}, "abstentions": {"nombre": 22463, "rapportInscrit": 57.04}, "inscrits": 39379}