{"inscrits": 6936, "votants": {"rapportInscrit": 57.73, "nombre": 4004}, "exprimes": {"rapportVotant": 88.71, "rapportInscrit": 51.21, "nombre": 3552}, "BC-SOC": {"rapportExprime": 50.23, "rapportInscrit": 25.72, "nombre": 1784, "nom": "Mme MEYRONEINC Christiane et M. SALAT G\u00e9rard"}, "blancs": {"rapportVotant": 7.44, "rapportInscrit": 4.3, "nombre": 298}, "nuls": {"rapportVotant": 3.85, "rapportInscrit": 2.22, "nombre": 154}, "abstentions": {"rapportInscrit": 42.27, "nombre": 2932}, "BC-DVD": {"rapportExprime": 49.77, "rapportInscrit": 25.49, "nombre": 1768, "nom": "M. BOS Christian et Mme GUIBERT Martine"}}