{"blancs": {"rapportVotant": 3.12, "nombre": 304, "rapportInscrit": 1.53}, "votants": {"nombre": 9729, "rapportInscrit": 48.81}, "BC-UG": {"nombre": 3990, "nom": "Mme COURTINE Fran\u00e7oise et M. LACROIX Guillaume", "rapportExprime": 43.02, "rapportInscrit": 20.01}, "exprimes": {"rapportVotant": 95.33, "nombre": 9275, "rapportInscrit": 46.54}, "nuls": {"rapportVotant": 1.54, "nombre": 150, "rapportInscrit": 0.75}, "abstentions": {"nombre": 10202, "rapportInscrit": 51.19}, "inscrits": 19931, "BC-UD": {"nombre": 5285, "nom": "Mme MARECHAL H\u00e9l\u00e8ne et M. PERRET Bernard", "rapportExprime": 56.98, "rapportInscrit": 26.51}}