{"blancs": {"rapportVotant": 1.91, "nombre": 187, "rapportInscrit": 0.96}, "votants": {"nombre": 9811, "rapportInscrit": 50.47}, "BC-UG": {"nombre": 3554, "nom": "Mme BOUVIER Josiane et M. GOUBET Pierre", "rapportExprime": 37.14, "rapportInscrit": 18.28}, "BC-FN": {"nombre": 2336, "nom": "M. GOBET Patrice et Mme LABROSSE Patricia", "rapportExprime": 24.41, "rapportInscrit": 12.01}, "exprimes": {"rapportVotant": 97.52, "nombre": 9568, "rapportInscrit": 49.22}, "nuls": {"rapportVotant": 0.57, "nombre": 56, "rapportInscrit": 0.29}, "abstentions": {"nombre": 9627, "rapportInscrit": 49.53}, "inscrits": 19438, "BC-UD": {"nombre": 3678, "nom": "M. GAITET Jean-Pierre et Mme TERRIER Caroline", "rapportExprime": 38.44, "rapportInscrit": 18.92}}