{"blancs": {"rapportVotant": 10.32, "nombre": 1047, "rapportInscrit": 5.64}, "votants": {"nombre": 10141, "rapportInscrit": 54.64}, "BC-FN": {"nombre": 3377, "nom": "M. GANNAT Pascal et Mme L'H\u00d4TE Annie", "rapportExprime": 38.86, "rapportInscrit": 18.19}, "BC-UMP": {"nombre": 5314, "nom": "Mme PAVY-MORANCAIS B\u00e9atrice et M. VALLIENNE R\u00e9gis", "rapportExprime": 61.14, "rapportInscrit": 28.63}, "exprimes": {"rapportVotant": 85.7, "nombre": 8691, "rapportInscrit": 46.83}, "nuls": {"rapportVotant": 3.97, "nombre": 403, "rapportInscrit": 2.17}, "abstentions": {"nombre": 8419, "rapportInscrit": 45.36}, "inscrits": 18560}