{"inscrits": 10313, "votants": {"rapportInscrit": 55.75, "nombre": 5749}, "BC-UD": {"rapportExprime": 20.91, "rapportInscrit": 11.16, "nombre": 1151, "nom": "M. MERLIN Jean-Marie et Mme PIAT Martine"}, "exprimes": {"rapportVotant": 95.74, "rapportInscrit": 53.37, "nombre": 5504}, "BC-COM": {"rapportExprime": 7.47, "rapportInscrit": 3.98, "nombre": 411, "nom": "Mme BENAGLIA Magali et M. CANTON Nicolas"}, "blancs": {"rapportVotant": 2.84, "rapportInscrit": 1.58, "nombre": 163}, "nuls": {"rapportVotant": 1.43, "rapportInscrit": 0.8, "nombre": 82}, "abstentions": {"rapportInscrit": 44.25, "nombre": 4564}, "BC-FN": {"rapportExprime": 34.39, "rapportInscrit": 18.35, "nombre": 1893, "nom": "M. GUITTON Jordan et Mme MAUCLAIR Morgane"}, "BC-DVD": {"rapportExprime": 37.23, "rapportInscrit": 19.86, "nombre": 2049, "nom": "M. BERNIER Guy et Mme GAUDY Solange"}}