{"inscrits": 30088, "blancs": {"rapportVotant": 3.38, "rapportInscrit": 1.8, "nombre": 543}, "BC-DIV": {"rapportExprime": 5.13, "rapportInscrit": 2.61, "nombre": 787, "nom": "Mme EYSSALET Nadine et M. JAMET Thierry"}, "abstentions": {"rapportInscrit": 46.55, "nombre": 14006}, "BC-FN": {"rapportExprime": 21.02, "rapportInscrit": 10.7, "nombre": 3222, "nom": "M. BREUIL Alain et Mme LUSSAUD Barbara"}, "exprimes": {"rapportVotant": 95.33, "rapportInscrit": 50.95, "nombre": 15331}, "votants": {"rapportInscrit": 53.45, "nombre": 16082}, "BC-DVG": {"rapportExprime": 9.13, "rapportInscrit": 4.64, "nombre": 1399, "nom": "Mme GUIGNARD Corine et M. PEAUDEAU Vincent"}, "BC-UD": {"rapportExprime": 42.16, "rapportInscrit": 21.48, "nombre": 6463, "nom": "M. GIRARD Patrick et Mme VAN GOETHEM Christiane"}, "BC-DLF": {"rapportExprime": 4.09, "rapportInscrit": 2.08, "nombre": 627, "nom": "M. BOISTEAU Christian et Mme GU\u00c9NOL\u00c9 Armelle"}, "BC-SOC": {"rapportExprime": 18.48, "rapportInscrit": 9.41, "nombre": 2833, "nom": "Mme GOLLY Catherine et M. VERGER Alain"}, "nuls": {"rapportVotant": 1.29, "rapportInscrit": 0.69, "nombre": 208}}