{"blancs": {"rapportVotant": 9.02, "nombre": 298, "rapportInscrit": 3.83}, "votants": {"nombre": 3302, "rapportInscrit": 42.42}, "BC-UG": {"nombre": 1156, "nom": "M. CAUSIN Axel et Mme EL-FAQIR Yasmina", "rapportExprime": 40.63, "rapportInscrit": 14.85}, "exprimes": {"rapportVotant": 86.16, "nombre": 2845, "rapportInscrit": 36.55}, "nuls": {"rapportVotant": 4.82, "nombre": 159, "rapportInscrit": 2.04}, "abstentions": {"nombre": 4482, "rapportInscrit": 57.58}, "inscrits": 7784, "BC-DVD": {"nombre": 1689, "nom": "M. FLAMERION Paul et Mme PAZDZIOR Catherine", "rapportExprime": 59.37, "rapportInscrit": 21.69}}