{"blancs": {"rapportVotant": 5.11, "nombre": 437, "rapportInscrit": 2.62}, "votants": {"nombre": 8545, "rapportInscrit": 51.2}, "BC-FN": {"nombre": 2972, "nom": "M. BRASSEUR Johnny et Mme VIGNOT Sandrine", "rapportExprime": 37.38, "rapportInscrit": 17.8}, "BC-UMP": {"nombre": 4978, "nom": "Mme BERAT Danielle et M. SAVARY Ren\u00e9-Paul", "rapportExprime": 62.62, "rapportInscrit": 29.82}, "exprimes": {"rapportVotant": 93.04, "nombre": 7950, "rapportInscrit": 47.64}, "nuls": {"rapportVotant": 1.85, "nombre": 158, "rapportInscrit": 0.95}, "abstentions": {"nombre": 8143, "rapportInscrit": 48.8}, "inscrits": 16688}