{"inscrits": 29579, "BC-FG": {"rapportExprime": 6.41, "rapportInscrit": 3.15, "nombre": 934, "nom": "M. CHAIGNE Pierrick et Mme LAUMONT Danielle"}, "blancs": {"rapportVotant": 2.77, "rapportInscrit": 1.43, "nombre": 423}, "abstentions": {"rapportInscrit": 48.46, "nombre": 14333}, "BC-FN": {"rapportExprime": 14.46, "rapportInscrit": 7.12, "nombre": 2108, "nom": "M. LESTRADE Jean-Michel et Mme ROY Catherine"}, "BC-DVD": {"rapportExprime": 3.11, "rapportInscrit": 1.53, "nombre": 454, "nom": "Mme BARREAU Marion et M. MAILLOT Thierry"}, "exprimes": {"rapportVotant": 95.61, "rapportInscrit": 49.28, "nombre": 14576}, "votants": {"rapportInscrit": 51.54, "nombre": 15246}, "BC-VEC": {"rapportExprime": 6.92, "rapportInscrit": 3.41, "nombre": 1009, "nom": "Mme BESSON Fran\u00e7oise et M. RAYNAUD Michel"}, "BC-UD": {"rapportExprime": 22.57, "rapportInscrit": 11.12, "nombre": 3290, "nom": "M. ABDALLAH Malik et Mme RAMBAUD-BOSSARD Christine"}, "BC-SOC": {"rapportExprime": 35.28, "rapportInscrit": 17.38, "nombre": 5142, "nom": "Mme BULTEAU Sylviane et M. IBARRA St\u00e9phane"}, "nuls": {"rapportVotant": 1.62, "rapportInscrit": 0.84, "nombre": 247}}