{"BC-UG": {"rapportExprime": 41.69, "rapportInscrit": 22.64, "nombre": 4280, "nom": "Mme BENEDINI Catherine et M. STOTER Jean-Jacques"}, "inscrits": 18903, "votants": {"rapportInscrit": 57.21, "nombre": 10814}, "BC-UD": {"rapportExprime": 23.17, "rapportInscrit": 12.58, "nombre": 2379, "nom": "Mme LOUISE Emmanuelle et M. TREILHOU Nicolas"}, "exprimes": {"rapportVotant": 94.94, "rapportInscrit": 54.31, "nombre": 10267}, "blancs": {"rapportVotant": 3.12, "rapportInscrit": 1.78, "nombre": 337}, "nuls": {"rapportVotant": 1.94, "rapportInscrit": 1.11, "nombre": 210}, "abstentions": {"rapportInscrit": 42.79, "nombre": 8089}, "BC-FN": {"rapportExprime": 35.14, "rapportInscrit": 19.08, "nombre": 3608, "nom": "Mme CAUCHE Lydie et M. SIMON Jean-Marc"}}